{"blocks": {"first_token_idx_list": [1, 3, 4, 6, 7, 9, 11, 12, 14, 16, 18, 23, 24, 35, 39, 42, 46, 53, 56, 60, 65, 69, 87, 92, 99, 111, 125, 159, 164, 174], "boxes": [[61, 207, 97, 221], [61, 235, 129, 249], [134, 236, 156, 250], [60, 261, 138, 276], [59, 320, 119, 337], [59, 348, 119, 363], [191, 321, 247, 335], [56, 549, 80, 562], [56, 591, 92, 604], [54, 626, 100, 639], [501, 839, 623, 871], [527, 162, 621, 189], [214, 94, 455, 140], [60, 177, 149, 192], [196, 177, 232, 194], [191, 207, 299, 222], [193, 221, 346, 252], [74, 292, 164, 307], [191, 292, 296, 308], [193, 348, 422, 365], [59, 377, 167, 393], [168, 404, 527, 437], [56, 462, 153, 477], [183, 465, 416, 540], [182, 626, 575, 641], [180, 652, 547, 681], [179, 697, 532, 740], [53, 751, 101, 767], [53, 796, 115, 824], [531, 193, 623, 248]]}, "words": [{"text": "DATE:", "tokens": [3058, 1024], "boundingBox": [[61, 207], [97, 207], [97, 221], [61, 221]]}, {"text": "INITIATED", "tokens": [7531], "boundingBox": [[61, 235], [129, 235], [129, 249], [61, 249]]}, {"text": "BY:", "tokens": [2011, 1024], "boundingBox": [[134, 236], [156, 236], [156, 250], [134, 250]]}, {"text": "COMPLETION", "tokens": [6503], "boundingBox": [[60, 261], [138, 261], [138, 276], [60, 276]]}, {"text": "COUNTRY:", "tokens": [2406, 1024], "boundingBox": [[59, 320], [119, 320], [119, 337], [59, 337]]}, {"text": "PRODUCT:", "tokens": [4031, 1024], "boundingBox": [[59, 348], [119, 348], [119, 363], [59, 363]]}, {"text": "BELGIUM", "tokens": [5706], "boundingBox": [[191, 321], [247, 321], [247, 335], [191, 335]]}, {"text": "BY:", "tokens": [2011, 1024], "boundingBox": [[56, 549], [80, 549], [80, 562], [56, 562]]}, {"text": "DATE:", "tokens": [3058, 1024], "boundingBox": [[56, 591], [92, 591], [92, 604], [56, 604]]}, {"text": "NOTES:", "tokens": [3964, 1024], "boundingBox": [[54, 626], [100, 626], [100, 639], [54, 639]]}, {"text": "620429480", "tokens": [23612, 20958, 2683, 18139, 2692], "boundingBox": [[501, 839], [623, 839], [623, 871], [501, 871]]}, {"text": "RECEIVED", "tokens": [2363], "boundingBox": [[527, 162], [621, 162], [621, 189], [527, 189]]}, {"text": "SERVICE", "tokens": [2326], "boundingBox": [[237, 94], [289, 94], [289, 109], [237, 109]]}, {"text": "REQUEST", "tokens": [5227], "boundingBox": [[293, 95], [346, 95], [346, 108], [293, 108]]}, {"text": "FROM", "tokens": [2013], "boundingBox": [[352, 95], [384, 95], [384, 108], [352, 108]]}, {"text": "R", "tokens": [1054], "boundingBox": [[388, 94], [396, 94], [396, 109], [388, 109]]}, {"text": "&", "tokens": [1004], "boundingBox": [[397, 95], [404, 95], [404, 109], [397, 109]]}, {"text": "D", "tokens": [1040], "boundingBox": [[402, 96], [412, 96], [412, 107], [402, 107]]}, {"text": "BY", "tokens": [2011], "boundingBox": [[418, 96], [435, 96], [435, 107], [418, 107]]}, {"text": "INTERNATIONAL", "tokens": [2248], "boundingBox": [[214, 122], [310, 122], [310, 139], [214, 139]]}, {"text": "LICENSEE", "tokens": [6105, 2063], "boundingBox": [[314, 122], [377, 122], [377, 140], [314, 140]]}, {"text": "OPERATIONS", "tokens": [3136], "boundingBox": [[381, 123], [455, 123], [455, 138], [381, 138]]}, {"text": "REQUEST", "tokens": [5227], "boundingBox": [[60, 177], [116, 177], [116, 191], [60, 191]]}, {"text": "NO.:", "tokens": [2053, 1012, 1024], "boundingBox": [[120, 179], [149, 179], [149, 192], [120, 192]]}, {"text": "25-", "tokens": [2423, 1011], "boundingBox": [[196, 177], [217, 177], [217, 194], [196, 194]]}, {"text": "84", "tokens": [6391], "boundingBox": [[215, 179], [232, 179], [232, 193], [215, 193]]}, {"text": "March", "tokens": [2233], "boundingBox": [[191, 207], [233, 207], [233, 221], [191, 221]]}, {"text": "27,", "tokens": [2676, 1010], "boundingBox": [[237, 207], [258, 207], [258, 222], [237, 222]]}, {"text": "1984", "tokens": [3118], "boundingBox": [[267, 207], [299, 207], [299, 221], [267, 221]]}, {"text": "P.", "tokens": [1052, 1012], "boundingBox": [[193, 235], [207, 235], [207, 250], [193, 250]]}, {"text": "H.", "tokens": [1044, 1012], "boundingBox": [[215, 235], [230, 235], [230, 250], [215, 250]]}, {"text": "HARPER", "tokens": [8500], "boundingBox": [[236, 235], [282, 235], [282, 252], [236, 252]]}, {"text": "PHH", "tokens": [6887, 2232], "boundingBox": [[297, 221], [346, 221], [346, 252], [297, 252]]}, {"text": "TARGET", "tokens": [4539], "boundingBox": [[74, 292], [120, 292], [120, 307], [74, 307]]}, {"text": "DATE:", "tokens": [3058, 1024], "boundingBox": [[126, 292], [164, 292], [164, 307], [126, 307]]}, {"text": "April", "tokens": [2258], "boundingBox": [[191, 293], [230, 293], [230, 308], [191, 308]]}, {"text": "13,", "tokens": [2410, 1010], "boundingBox": [[237, 292], [259, 292], [259, 307], [237, 307]]}, {"text": "1984", "tokens": [3118], "boundingBox": [[265, 293], [296, 293], [296, 307], [265, 307]]}, {"text": "LUCKY", "tokens": [5341], "boundingBox": [[193, 349], [231, 349], [231, 363], [193, 363]]}, {"text": "STRIKE", "tokens": [4894], "boundingBox": [[236, 349], [281, 349], [281, 364], [236, 364]]}, {"text": "Filter", "tokens": [11307], "boundingBox": [[286, 348], [332, 348], [332, 365], [286, 365]]}, {"text": "and", "tokens": [1998], "boundingBox": [[337, 352], [364, 352], [364, 363], [337, 363]]}, {"text": "VICEROY", "tokens": [19007], "boundingBox": [[366, 349], [422, 349], [422, 364], [366, 364]]}, {"text": "NATURE", "tokens": [3267], "boundingBox": [[59, 378], [106, 378], [106, 393], [59, 393]]}, {"text": "OF", "tokens": [1997], "boundingBox": [[110, 377], [125, 377], [125, 391], [110, 391]]}, {"text": "WORK:", "tokens": [2147, 1024], "boundingBox": [[128, 378], [167, 378], [167, 392], [128, 392]]}, {"text": "Advise", "tokens": [18012], "boundingBox": [[168, 405], [215, 405], [215, 420], [168, 420]]}, {"text": "if", "tokens": [2065], "boundingBox": [[221, 406], [238, 406], [238, 419], [221, 419]]}, {"text": "locally", "tokens": [7246], "boundingBox": [[243, 404], [295, 404], [295, 421], [243, 421]]}, {"text": "obtained", "tokens": [4663], "boundingBox": [[300, 408], [361, 408], [361, 422], [300, 422]]}, {"text": "Yucatan", "tokens": [28631], "boundingBox": [[366, 406], [420, 406], [420, 421], [366, 421]]}, {"text": "Honey", "tokens": [6861], "boundingBox": [[423, 406], [464, 406], [464, 421], [423, 421]]}, {"text": "(sample", "tokens": [1006, 7099], "boundingBox": [[471, 408], [523, 408], [523, 422], [471, 422]]}, {"text": "enclosed)", "tokens": [10837, 1007], "boundingBox": [[168, 422], [235, 422], [235, 433], [168, 433]]}, {"text": "is", "tokens": [2003], "boundingBox": [[243, 423], [260, 423], [260, 434], [243, 434]]}, {"text": "an", "tokens": [2019], "boundingBox": [[264, 423], [281, 423], [281, 433], [264, 433]]}, {"text": "acceptable", "tokens": [11701], "boundingBox": [[285, 422], [360, 422], [360, 436], [285, 436]]}, {"text": "substitute", "tokens": [7681], "boundingBox": [[366, 423], [440, 423], [440, 437], [366, 437]]}, {"text": "for", "tokens": [2005], "boundingBox": [[446, 423], [470, 423], [470, 436], [446, 436]]}, {"text": "HALWAY.", "tokens": [11085, 4576, 1012], "boundingBox": [[475, 425], [527, 425], [527, 436], [475, 436]]}, {"text": "R", "tokens": [1054], "boundingBox": [[56, 462], [67, 462], [67, 476], [56, 476]]}, {"text": "&", "tokens": [1004], "boundingBox": [[67, 464], [73, 464], [73, 477], [67, 477]]}, {"text": "D", "tokens": [1040], "boundingBox": [[73, 464], [81, 464], [81, 475], [73, 475]]}, {"text": "COMMENTS:", "tokens": [7928, 1024], "boundingBox": [[87, 462], [153, 462], [153, 476], [87, 476]]}, {"text": "Target", "tokens": [4539], "boundingBox": [[183, 472], [251, 472], [251, 501], [183, 501]]}, {"text": "the", "tokens": [1996], "boundingBox": [[261, 468], [306, 468], [306, 490], [261, 490]]}, {"text": "P", "tokens": [1052], "boundingBox": [[197, 501], [238, 501], [238, 540], [197, 540]]}, {"text": "A", "tokens": [1037], "boundingBox": [[260, 501], [294, 501], [294, 530], [260, 530]]}, {"text": "29Mar", "tokens": [2756, 7849], "boundingBox": [[323, 497], [382, 497], [382, 521], [323, 521]]}, {"text": "84", "tokens": [6391], "boundingBox": [[384, 489], [416, 489], [416, 517], [384, 517]]}, {"text": "a)", "tokens": [1037, 1007], "boundingBox": [[182, 626], [195, 626], [195, 639], [182, 639]]}, {"text": "Nature", "tokens": [3267], "boundingBox": [[209, 626], [255, 626], [255, 640], [209, 640]]}, {"text": "of", "tokens": [1997], "boundingBox": [[261, 627], [278, 627], [278, 638], [261, 638]]}, {"text": "work", "tokens": [2147], "boundingBox": [[282, 627], [313, 627], [313, 640], [282, 640]]}, {"text": "should", "tokens": [2323], "boundingBox": [[318, 626], [365, 626], [365, 641], [318, 641]]}, {"text": "be", "tokens": [2022], "boundingBox": [[370, 627], [385, 627], [385, 641], [370, 641]]}, {"text": "specified", "tokens": [9675], "boundingBox": [[392, 627], [459, 627], [459, 641], [392, 641]]}, {"text": "in", "tokens": [1999], "boundingBox": [[464, 627], [481, 627], [481, 641], [464, 641]]}, {"text": "exact", "tokens": [6635], "boundingBox": [[486, 628], [525, 628], [525, 641], [486, 641]]}, {"text": "terms.", "tokens": [3408, 1012], "boundingBox": [[532, 628], [575, 628], [575, 641], [532, 641]]}, {"text": "b)", "tokens": [1038, 1007], "boundingBox": [[180, 652], [194, 652], [194, 667], [180, 667]]}, {"text": "R", "tokens": [1054], "boundingBox": [[209, 655], [219, 655], [219, 666], [209, 666]]}, {"text": "&", "tokens": [1004], "boundingBox": [[218, 655], [225, 655], [225, 666], [218, 666]]}, {"text": "D", "tokens": [1040], "boundingBox": [[223, 656], [234, 656], [234, 667], [223, 667]]}, {"text": "should", "tokens": [2323], "boundingBox": [[237, 655], [284, 655], [284, 668], [237, 668]]}, {"text": "advise", "tokens": [18012], "boundingBox": [[289, 656], [336, 656], [336, 667], [289, 667]]}, {"text": "if", "tokens": [2065], "boundingBox": [[342, 655], [357, 655], [357, 668], [342, 668]]}, {"text": "completion", "tokens": [6503], "boundingBox": [[363, 656], [438, 656], [438, 670], [363, 670]]}, {"text": "date", "tokens": [3058], "boundingBox": [[443, 655], [474, 655], [474, 670], [443, 670]]}, {"text": "cannot", "tokens": [3685], "boundingBox": [[479, 658], [525, 658], [525, 669], [479, 669]]}, {"text": "be", "tokens": [2022], "boundingBox": [[529, 656], [547, 656], [547, 669], [529, 669]]}, {"text": "met.", "tokens": [2777, 1012], "boundingBox": [[208, 670], [240, 670], [240, 681], [208, 681]]}, {"text": "c)", "tokens": [1039, 1007], "boundingBox": [[179, 698], [196, 698], [196, 711], [179, 711]]}, {"text": "Two", "tokens": [2048], "boundingBox": [[209, 700], [234, 700], [234, 708], [209, 708]]}, {"text": "copies", "tokens": [4809], "boundingBox": [[240, 698], [282, 698], [282, 711], [240, 711]]}, {"text": "of", "tokens": [1997], "boundingBox": [[289, 698], [306, 698], [306, 711], [289, 711]]}, {"text": "this", "tokens": [2023], "boundingBox": [[313, 698], [342, 698], [342, 711], [313, 711]]}, {"text": "form", "tokens": [2433], "boundingBox": [[349, 698], [378, 698], [378, 712], [349, 712]]}, {"text": "to", "tokens": [2000], "boundingBox": [[385, 698], [400, 698], [400, 711], [385, 711]]}, {"text": "be", "tokens": [2022], "boundingBox": [[405, 700], [423, 700], [423, 711], [405, 711]]}, {"text": "sent", "tokens": [2741], "boundingBox": [[429, 700], [458, 700], [458, 711], [429, 711]]}, {"text": "to", "tokens": [2000], "boundingBox": [[466, 700], [481, 700], [481, 711], [466, 711]]}, {"text": "R", "tokens": [1054], "boundingBox": [[487, 698], [495, 698], [495, 712], [487, 712]]}, {"text": "&", "tokens": [1004], "boundingBox": [[494, 700], [501, 700], [501, 711], [494, 711]]}, {"text": "D", "tokens": [1040], "boundingBox": [[501, 698], [511, 698], [511, 711], [501, 711]]}, {"text": "by", "tokens": [2011], "boundingBox": [[514, 697], [532, 697], [532, 712], [514, 712]]}, {"text": "initiator", "tokens": [1999, 29050, 4263], "boundingBox": [[209, 711], [277, 711], [277, 728], [209, 728]]}, {"text": "and", "tokens": [1998], "boundingBox": [[282, 714], [306, 714], [306, 725], [282, 725]]}, {"text": "R", "tokens": [1054], "boundingBox": [[311, 712], [321, 712], [321, 725], [311, 725]]}, {"text": "&", "tokens": [1004], "boundingBox": [[320, 714], [327, 714], [327, 725], [320, 725]]}, {"text": "D", "tokens": [1040], "boundingBox": [[325, 712], [335, 712], [335, 723], [325, 723]]}, {"text": "is", "tokens": [2003], "boundingBox": [[341, 714], [358, 714], [358, 725], [341, 725]]}, {"text": "to", "tokens": [2000], "boundingBox": [[363, 714], [377, 714], [377, 725], [363, 725]]}, {"text": "return", "tokens": [2709], "boundingBox": [[384, 714], [430, 714], [430, 727], [384, 727]]}, {"text": "to", "tokens": [2000], "boundingBox": [[436, 714], [451, 714], [451, 727], [436, 727]]}, {"text": "T.", "tokens": [1056, 1012], "boundingBox": [[457, 712], [471, 712], [471, 725], [457, 725]]}, {"text": "O.", "tokens": [1051, 1012], "boundingBox": [[471, 712], [486, 712], [486, 723], [471, 723]]}, {"text": "one", "tokens": [2028], "boundingBox": [[492, 715], [520, 715], [520, 726], [492, 726]]}, {"text": "completed", "tokens": [2949], "boundingBox": [[209, 726], [277, 726], [277, 739], [209, 739]]}, {"text": "copy.", "tokens": [6100, 1012], "boundingBox": [[284, 726], [318, 726], [318, 740], [284, 740]]}, {"text": "MH/", "tokens": [1049, 2232, 1013], "boundingBox": [[53, 751], [78, 751], [78, 766], [53, 766]]}, {"text": "enm", "tokens": [4372, 2213], "boundingBox": [[77, 756], [101, 756], [101, 767], [77, 767]]}, {"text": "0036/", "tokens": [4002, 21619, 1013], "boundingBox": [[53, 796], [92, 796], [92, 809], [53, 809]]}, {"text": "(r)", "tokens": [1006, 1054, 1007], "boundingBox": [[91, 797], [115, 797], [115, 808], [91, 808]]}, {"text": "#", "tokens": [1001], "boundingBox": [[54, 811], [62, 811], [62, 822], [54, 822]]}, {"text": "2894M", "tokens": [27054, 2549, 2213], "boundingBox": [[61, 811], [102, 811], [102, 824], [61, 824]]}, {"text": "APR", "tokens": [19804], "boundingBox": [[531, 193], [563, 193], [563, 214], [531, 214]]}, {"text": "2", "tokens": [1016], "boundingBox": [[577, 194], [590, 194], [590, 215], [577, 215]]}, {"text": "1984", "tokens": [3118], "boundingBox": [[594, 194], [623, 194], [623, 212], [594, 212]]}, {"text": "P.", "tokens": [1052, 1012], "boundingBox": [[545, 226], [565, 226], [565, 247], [545, 247]]}, {"text": "H.", "tokens": [1044, 1012], "boundingBox": [[564, 226], [582, 226], [582, 248], [564, 248]]}, {"text": "H.", "tokens": [1044, 1012], "boundingBox": [[582, 229], [600, 229], [600, 247], [582, 247]]}], "parse": {"class": {"O": [[10], [120, 121], [122, 123, 124, 125]], "HEADER": [[12, 13, 14, 15, 16, 17, 18, 19, 20, 21]], "QUESTION": [[0], [1], [2], [3], [4], [5], [7], [8], [9], [11], [22, 23], [33, 34], [43, 44, 45], [60, 61, 62, 63]], "ANSWER": [[6], [24, 25], [26, 27, 28], [29, 30, 31, 32], [35, 36, 37], [38, 39, 40, 41, 42], [46, 47, 48, 49, 50, 51, 52, 53, 54, 55, 56, 57, 58, 59], [64, 65, 66, 67, 68, 69], [70, 71, 72, 73, 74, 75, 76, 77, 78, 79], [80, 81, 82, 83, 84, 85, 86, 87, 88, 89, 90, 91], [92, 93, 94, 95, 96, 97, 98, 99, 100, 101, 102, 103, 104, 105, 106, 107, 108, 109, 110, 111, 112, 113, 114, 115, 116, 117, 118, 119], [126, 127, 128, 129, 130, 131]]}, "relations": [[0, 26], [1, 29], [2, 29], [4, 6], [5, 38], [9, 70], [9, 80], [9, 92], [11, 126], [22, 24], [33, 35], [43, 46], [60, 64]]}, "meta": {"image_path": "training_data/images/0000990274.png", "imageSize": {"width": 762, "height": 1000}, "voca": "bert-base-uncased"}}