{"blocks": {"first_token_idx_list": [1, 3, 5, 10, 11, 12, 13, 14, 15, 18, 22, 27, 30, 31, 32, 37, 42, 46, 49, 56, 61, 65, 70, 75, 81, 91, 96, 101, 105, 112, 117, 123, 125, 134, 137, 140, 145, 150, 152, 154, 156, 158, 161, 164, 170, 174, 181], "boxes": [[78, 124, 100, 139], [77, 152, 122, 166], [608, 126, 664, 139], [233, 453, 244, 464], [233, 480, 244, 493], [429, 482, 440, 495], [430, 494, 440, 507], [306, 563, 348, 576], [413, 811, 462, 836], [676, 768, 698, 870], [640, 934, 683, 947], [50, 934, 110, 948], [541, 589, 575, 602], [549, 615, 576, 630], [215, 124, 304, 139], [499, 126, 584, 141], [216, 149, 298, 166], [216, 179, 319, 194], [78, 177, 179, 193], [258, 233, 485, 247], [77, 288, 185, 302], [81, 314, 188, 330], [228, 314, 285, 328], [216, 286, 395, 303], [272, 370, 471, 386], [75, 372, 260, 385], [74, 453, 159, 466], [75, 468, 167, 481], [77, 480, 186, 494], [77, 494, 184, 507], [306, 454, 379, 465], [307, 426, 359, 439], [496, 453, 595, 467], [497, 468, 573, 479], [306, 466, 376, 479], [306, 480, 363, 493], [306, 496, 363, 508], [306, 508, 362, 519], [499, 564, 634, 575], [304, 589, 400, 603], [307, 620, 413, 633], [77, 728, 131, 741], [78, 756, 257, 767], [324, 754, 405, 768], [77, 796, 151, 808], [74, 823, 345, 836], [77, 877, 472, 893]]}, "words": [{"text": "TO:", "tokens": [2000, 1024], "boundingBox": [[78, 124], [100, 124], [100, 139], [78, 139]]}, {"text": "FROM:", "tokens": [2013, 1024], "boundingBox": [[77, 152], [122, 152], [122, 166], [77, 166]]}, {"text": "1/24/97", "tokens": [1015, 1013, 2484, 1013, 5989], "boundingBox": [[608, 126], [664, 126], [664, 139], [608, 139]]}, {"text": "2", "tokens": [1016], "boundingBox": [[233, 453], [244, 453], [244, 464], [233, 464]]}, {"text": "1", "tokens": [1015], "boundingBox": [[233, 480], [244, 480], [244, 493], [233, 493]]}, {"text": "1", "tokens": [1015], "boundingBox": [[429, 482], [440, 482], [440, 495], [429, 495]]}, {"text": "1", "tokens": [1015], "boundingBox": [[430, 494], [440, 494], [440, 507], [430, 507]]}, {"text": "ITEMS", "tokens": [5167], "boundingBox": [[306, 563], [348, 563], [348, 576], [306, 576]]}, {"text": "zbulan", "tokens": [1062, 28507, 2078], "boundingBox": [[413, 811], [462, 811], [462, 836], [413, 836]]}, {"text": "82254765", "tokens": [6445, 17788, 22610, 26187], "boundingBox": [[676, 768], [698, 768], [698, 870], [676, 870]]}, {"text": "01/17/97", "tokens": [5890, 1013, 2459, 1013, 5989], "boundingBox": [[640, 934], [683, 934], [683, 947], [640, 947]]}, {"text": "REQFORM", "tokens": [2128, 4160, 14192], "boundingBox": [[50, 934], [110, 934], [110, 948], [50, 948]]}, {"text": "1500", "tokens": [10347], "boundingBox": [[541, 589], [575, 589], [575, 602], [541, 602]]}, {"text": "500", "tokens": [3156], "boundingBox": [[549, 615], [576, 615], [576, 630], [549, 630]]}, {"text": "K.", "tokens": [1047, 1012], "boundingBox": [[215, 126], [228, 126], [228, 139], [215, 139]]}, {"text": "A.", "tokens": [1037, 1012], "boundingBox": [[232, 124], [243, 124], [243, 138], [232, 138]]}, {"text": "SPARROW", "tokens": [19479], "boundingBox": [[244, 127], [304, 127], [304, 138], [244, 138]]}, {"text": "DATE", "tokens": [3058], "boundingBox": [[499, 127], [533, 127], [533, 138], [499, 138]]}, {"text": "TO", "tokens": [2000], "boundingBox": [[532, 126], [552, 126], [552, 139], [532, 139]]}, {"text": "NYO:", "tokens": [6396, 2080, 1024], "boundingBox": [[552, 128], [584, 128], [584, 141], [552, 141]]}, {"text": "S.", "tokens": [1055, 1012], "boundingBox": [[216, 151], [233, 151], [233, 164], [216, 164]]}, {"text": "Reindel", "tokens": [27788, 9247], "boundingBox": [[244, 149], [298, 149], [298, 166], [244, 166]]}, {"text": "Nassau/", "tokens": [14646, 1013], "boundingBox": [[216, 179], [283, 179], [283, 193], [216, 193]]}, {"text": "107", "tokens": [10550], "boundingBox": [[292, 179], [319, 179], [319, 194], [292, 194]]}, {"text": "DIV.", "tokens": [4487, 2615, 1012], "boundingBox": [[78, 177], [106, 177], [106, 192], [78, 192]]}, {"text": "NAME/", "tokens": [2171, 1013], "boundingBox": [[108, 180], [154, 180], [154, 193], [108, 193]]}, {"text": "NO:", "tokens": [2053, 1024], "boundingBox": [[155, 179], [179, 179], [179, 193], [155, 193]]}, {"text": "1997", "tokens": [2722], "boundingBox": [[258, 233], [282, 233], [282, 247], [258, 247]]}, {"text": "SPECIAL", "tokens": [2569], "boundingBox": [[286, 235], [339, 235], [339, 246], [286, 246]]}, {"text": "EVENT", "tokens": [2724], "boundingBox": [[339, 235], [381, 235], [381, 246], [339, 246]]}, {"text": "REQUEST", "tokens": [5227], "boundingBox": [[384, 235], [444, 235], [444, 246], [384, 246]]}, {"text": "FORM", "tokens": [2433], "boundingBox": [[447, 235], [485, 235], [485, 246], [447, 246]]}, {"text": "NAME", "tokens": [2171], "boundingBox": [[77, 288], [116, 288], [116, 301], [77, 301]]}, {"text": "OF", "tokens": [1997], "boundingBox": [[117, 288], [135, 288], [135, 301], [117, 301]]}, {"text": "EVENT:", "tokens": [2724, 1024], "boundingBox": [[138, 288], [185, 288], [185, 302], [138, 302]]}, {"text": "\"DATE", "tokens": [1000, 3058], "boundingBox": [[81, 316], [117, 316], [117, 330], [81, 330]]}, {"text": "OF", "tokens": [1997], "boundingBox": [[122, 317], [139, 317], [139, 328], [122, 328]]}, {"text": "EVENT:", "tokens": [2724, 1024], "boundingBox": [[141, 314], [188, 314], [188, 328], [141, 328]]}, {"text": "3/18/97", "tokens": [1017, 1013, 2324, 1013, 5989], "boundingBox": [[228, 314], [285, 314], [285, 328], [228, 328]]}, {"text": "H.", "tokens": [1044, 1012], "boundingBox": [[216, 288], [233, 288], [233, 303], [216, 303]]}, {"text": "Levinson", "tokens": [20206, 3385], "boundingBox": [[243, 288], [311, 288], [311, 302], [243, 302]]}, {"text": "Tradeshow", "tokens": [14279, 14406], "boundingBox": [[320, 286], [395, 286], [395, 301], [320, 301]]}, {"text": "SAMPLE", "tokens": [7099], "boundingBox": [[272, 372], [319, 372], [319, 385], [272, 385]]}, {"text": "10'S", "tokens": [2184, 1005, 1055], "boundingBox": [[325, 370], [345, 370], [345, 383], [325, 383]]}, {"text": "(400", "tokens": [1006, 4278], "boundingBox": [[348, 373], [370, 373], [370, 384], [348, 384]]}, {"text": "PACKS", "tokens": [15173], "boundingBox": [[369, 372], [408, 372], [408, 385], [369, 385]]}, {"text": "PER", "tokens": [2566], "boundingBox": [[409, 370], [433, 370], [433, 384], [409, 384]]}, {"text": "CASE)", "tokens": [2553, 1007], "boundingBox": [[437, 372], [471, 372], [471, 386], [437, 386]]}, {"text": "SAMPLES/", "tokens": [8168, 1013], "boundingBox": [[75, 372], [142, 372], [142, 383], [75, 383]]}, {"text": "ITEMS", "tokens": [5167], "boundingBox": [[145, 373], [184, 373], [184, 384], [145, 384]]}, {"text": "REQUIRED:", "tokens": [3223, 1024], "boundingBox": [[186, 372], [260, 372], [260, 385], [186, 385]]}, {"text": "NEWPORT", "tokens": [9464], "boundingBox": [[74, 453], [137, 453], [137, 466], [74, 466]]}, {"text": "K.", "tokens": [1047, 1012], "boundingBox": [[138, 453], [149, 453], [149, 466], [138, 466]]}, {"text": "S.", "tokens": [1055, 1012], "boundingBox": [[148, 453], [159, 453], [159, 466], [148, 466]]}, {"text": "NEWPORT", "tokens": [9464], "boundingBox": [[75, 468], [136, 468], [136, 481], [75, 481]]}, {"text": "100's", "tokens": [2531, 1005, 1055], "boundingBox": [[140, 468], [167, 468], [167, 479], [140, 479]]}, {"text": "NEWPORT", "tokens": [9464], "boundingBox": [[77, 482], [137, 482], [137, 492], [77, 492]]}, {"text": "LTS", "tokens": [8318, 2015], "boundingBox": [[138, 480], [162, 480], [162, 494], [138, 494]]}, {"text": "K.", "tokens": [1047, 1012], "boundingBox": [[163, 480], [176, 480], [176, 494], [163, 494]]}, {"text": "S.", "tokens": [1055, 1012], "boundingBox": [[176, 480], [186, 480], [186, 493], [176, 493]]}, {"text": "NEWPORT", "tokens": [9464], "boundingBox": [[77, 494], [134, 494], [134, 505], [77, 505]]}, {"text": "LTS.", "tokens": [8318, 2015, 1012], "boundingBox": [[138, 494], [162, 494], [162, 507], [138, 507]]}, {"text": "100", "tokens": [2531], "boundingBox": [[166, 496], [184, 496], [184, 507], [166, 507]]}, {"text": "KENT", "tokens": [5982], "boundingBox": [[306, 454], [340, 454], [340, 464], [306, 464]]}, {"text": "III", "tokens": [3523], "boundingBox": [[342, 454], [356, 454], [356, 465], [342, 465]]}, {"text": "K.", "tokens": [1047, 1012], "boundingBox": [[355, 454], [368, 454], [368, 464], [355, 464]]}, {"text": "S.", "tokens": [1055, 1012], "boundingBox": [[369, 454], [379, 454], [379, 464], [369, 464]]}, {"text": "#", "tokens": [1001], "boundingBox": [[307, 429], [317, 429], [317, 437], [307, 437]]}, {"text": "CASES", "tokens": [3572], "boundingBox": [[320, 426], [359, 426], [359, 439], [320, 439]]}, {"text": "KENT", "tokens": [5982], "boundingBox": [[496, 454], [531, 454], [531, 465], [496, 465]]}, {"text": "GL", "tokens": [1043, 2140], "boundingBox": [[532, 454], [549, 454], [549, 467], [532, 467]]}, {"text": "LTS", "tokens": [8318, 2015], "boundingBox": [[552, 455], [573, 455], [573, 466], [552, 466]]}, {"text": "K.", "tokens": [1047, 1012], "boundingBox": [[574, 453], [585, 453], [585, 466], [574, 466]]}, {"text": "S.", "tokens": [1055, 1012], "boundingBox": [[587, 455], [595, 455], [595, 465], [587, 465]]}, {"text": "GL", "tokens": [1043, 2140], "boundingBox": [[535, 468], [553, 468], [553, 479], [535, 479]]}, {"text": "100", "tokens": [2531], "boundingBox": [[553, 469], [573, 469], [573, 477], [553, 477]]}, {"text": "KENT", "tokens": [5982], "boundingBox": [[306, 466], [340, 466], [340, 479], [306, 479]]}, {"text": "III", "tokens": [3523], "boundingBox": [[342, 469], [356, 469], [356, 477], [342, 477]]}, {"text": "100", "tokens": [2531], "boundingBox": [[358, 469], [376, 469], [376, 479], [358, 479]]}, {"text": "TRUE", "tokens": [2995], "boundingBox": [[306, 483], [342, 483], [342, 491], [306, 491]]}, {"text": "K.", "tokens": [1047, 1012], "boundingBox": [[344, 480], [352, 480], [352, 493], [344, 493]]}, {"text": "S.", "tokens": [1055, 1012], "boundingBox": [[353, 480], [363, 480], [363, 491], [353, 491]]}, {"text": "KENT", "tokens": [5982], "boundingBox": [[306, 496], [340, 496], [340, 504], [306, 504]]}, {"text": "K.", "tokens": [1047, 1012], "boundingBox": [[342, 497], [353, 497], [353, 508], [342, 508]]}, {"text": "S.", "tokens": [1055, 1012], "boundingBox": [[352, 496], [363, 496], [363, 507], [352, 507]]}, {"text": "KENT", "tokens": [5982], "boundingBox": [[306, 508], [340, 508], [340, 519], [306, 519]]}, {"text": "100", "tokens": [2531], "boundingBox": [[342, 508], [362, 508], [362, 519], [342, 519]]}, {"text": "QUANTITY", "tokens": [11712], "boundingBox": [[499, 564], [567, 564], [567, 575], [499, 575]]}, {"text": "REQUIRED", "tokens": [3223], "boundingBox": [[570, 564], [634, 564], [634, 575], [570, 575]]}, {"text": "BASEBALL", "tokens": [3598], "boundingBox": [[304, 589], [371, 589], [371, 603], [304, 603]]}, {"text": "CAP", "tokens": [6178], "boundingBox": [[376, 591], [400, 591], [400, 602], [376, 602]]}, {"text": "WATER", "tokens": [2300], "boundingBox": [[307, 620], [354, 620], [354, 631], [307, 631]]}, {"text": "BOTTLES", "tokens": [11015], "boundingBox": [[356, 620], [413, 620], [413, 633], [356, 633]]}, {"text": "SHIP", "tokens": [2911], "boundingBox": [[77, 728], [105, 728], [105, 741], [77, 741]]}, {"text": "TO:", "tokens": [2000, 1024], "boundingBox": [[109, 728], [131, 728], [131, 739], [109, 739]]}, {"text": "CUSTOMER", "tokens": [8013], "boundingBox": [[78, 757], [142, 757], [142, 767], [78, 767]]}, {"text": "SHIPPING", "tokens": [7829], "boundingBox": [[145, 756], [199, 756], [199, 767], [145, 767]]}, {"text": "NUMBER", "tokens": [2193], "boundingBox": [[204, 757], [257, 757], [257, 765], [204, 765]]}, {"text": "198-", "tokens": [20003, 1011], "boundingBox": [[324, 754], [345, 754], [345, 768], [324, 768]]}, {"text": "1160006", "tokens": [12904, 8889, 2692, 2575], "boundingBox": [[346, 754], [405, 754], [405, 767], [346, 767]]}, {"text": "NYO", "tokens": [6396, 2080], "boundingBox": [[77, 797], [106, 797], [106, 808], [77, 808]]}, {"text": "ONLY:", "tokens": [2069, 1024], "boundingBox": [[110, 796], [151, 796], [151, 807], [110, 807]]}, {"text": "DATE", "tokens": [3058], "boundingBox": [[74, 825], [109, 825], [109, 835], [74, 835]]}, {"text": "FORWARDED", "tokens": [2830, 2098], "boundingBox": [[112, 825], [190, 825], [190, 835], [112, 835]]}, {"text": "TO", "tokens": [2000], "boundingBox": [[191, 823], [208, 823], [208, 836], [191, 836]]}, {"text": "PROMOTION", "tokens": [4712], "boundingBox": [[209, 825], [284, 825], [284, 835], [209, 835]]}, {"text": "SERVICES:", "tokens": [2578, 1024], "boundingBox": [[285, 825], [345, 825], [345, 835], [285, 835]]}, {"text": "PLEASE", "tokens": [3531], "boundingBox": [[77, 878], [136, 878], [136, 891], [77, 891]]}, {"text": "ALLOW", "tokens": [3499], "boundingBox": [[138, 878], [184, 878], [184, 891], [138, 891]]}, {"text": "6", "tokens": [1020], "boundingBox": [[184, 880], [194, 880], [194, 890], [184, 890]]}, {"text": "WEEKS", "tokens": [3134], "boundingBox": [[193, 878], [238, 878], [238, 891], [193, 891]]}, {"text": "FOR", "tokens": [2005], "boundingBox": [[239, 880], [268, 880], [268, 893], [239, 893]]}, {"text": "PROCESSING", "tokens": [6364], "boundingBox": [[271, 880], [349, 880], [349, 893], [271, 893]]}, {"text": "OF", "tokens": [1997], "boundingBox": [[352, 880], [373, 880], [373, 893], [352, 893]]}, {"text": "YOUR", "tokens": [2115], "boundingBox": [[370, 878], [409, 878], [409, 891], [370, 891]]}, {"text": "REQUEST", "tokens": [5227], "boundingBox": [[412, 877], [472, 877], [472, 891], [412, 891]]}], "parse": {"class": {"O": [[9], [10], [11], [67, 68], [107, 108, 109, 110, 111, 112, 113, 114, 115]], "HEADER": [[27, 28, 29, 30, 31], [93, 94], [100, 101]], "QUESTION": [[0], [1], [7], [17, 18, 19], [24, 25, 26], [32, 33, 34], [35, 36, 37], [48, 49, 50], [51, 52, 53], [54, 55], [56, 57, 58, 59], [60, 61, 62], [63, 64, 65, 66], [69, 70, 71, 72, 73], [74, 75], [76, 77, 78], [79, 80, 81], [82, 83, 84], [85, 86], [87, 88], [95, 96, 97], [102, 103, 104, 105, 106]], "ANSWER": [[2], [3], [4], [5], [6], [8], [12], [13], [14, 15, 16], [20, 21], [22, 23], [38], [39, 40, 41], [42, 43, 44, 45, 46, 47], [89, 90], [91, 92], [98, 99]]}, "relations": [[0, 14], [1, 20], [7, 89], [7, 91], [17, 2], [24, 22], [32, 39], [35, 38], [48, 42], [51, 3], [56, 4], [79, 5], [82, 6], [87, 12], [87, 13], [93, 95], [95, 98], [100, 102], [102, 8]]}, "meta": {"image_path": "testing_data/images/82254765.png", "imageSize": {"width": 754, "height": 1000}, "voca": "bert-base-uncased"}}